{
    "id": 9138990,
    "name": "ReActive",
    "author": "Codex",
    "creators": ["Codex, FilleFjonk"],
    "verifier": "Codex",
    "verification": "https://youtu.be/ONXgvV3GoB8?si=5iWNhNiqireGklbY",
    "showcase": "",
    "percentToQualify": 100,
    "records": [
        {
            "user": "ZircleZ",
            "link": "",
            "percent": 100,
            "hz": 240
        },
        {
            "user": "Lemoncitooo",
            "link": "",
            "percent": 100,
            "hz": 240
        },
        {
            "user": "GW HyperActive",
            "link": "",
            "percent": 100,
            "hz": 240
        },
        {
            "user": "yoshi",
            "link": "",
            "percent": 100,
            "hz": 240
        },
        {
            "user": "Chonkey",
            "link": "",
            "percent": 100,
            "hz": 240
        },
        {
            "user": "LifelessComputer",
            "link": "",
            "percent": 100,
            "hz": 240
        },
        {
            "user": "deadbush",
            "link": "",
            "percent": 100,
            "hz": 240    
        },
        {
            "user": "TheoSi",
            "link": "",
            "percent": 100,
            "hz": 240
        },
        {
            "user": "JoacoPe",
            "link": "",
            "percent": 100,
            "hz": 240
        },
        {
            "user": "BraiinFog",
            "link": "https://www.youtube.com/watch?v=1p8rG1G8AN0",
            "percent": 100,
            "hz": 240
        }
    ]
}








