{
    "id": 88785961,
    "name": "Redlight Blacklight",
    "author": "Raivolt",
    "creators": ["Raivolt, GiggsRH"],
    "verifier": "Raivolt",
    "verification": "https://youtu.be/UDeuiqUMHjY?si=F13-D6LrjkSzoUwB",
    "showcase": "",
    "percentToQualify": 100,
    "records": [
        {
            "user": "[FAIRY] Angeb",
            "link": "",
            "percent": 100,
            "hz": 360
        },
        {
            "user": "yoshi",
            "link": "",
            "percent": 100,
            "hz": 360
        },
        {
            "user": "Fawxu",
            "link": "",
            "percent": 100,
            "hz": 360
        },
        {
            "user": "kubalolxd7",
            "link": "",
            "percent": 100,
            "hz": 360
        },
        {
            "user": "dragnalus",
            "link": "https://youtu.be/N_xFRxJavco?si=XU8EqEPCS6Mn2H5o",
            "percent": 100,
            "hz": 360
        },
        {
            "user": "LifelessComputer",
            "link": "",
            "percent": 100,
            "hz": 360
        },
        {
            "user": "Chonkey",
            "link": "",
            "percent": 100,
            "hz": 360
        },
        {
            "user": "JoacoPe",
            "link": "",
            "percent": 100,
            "hz": 360
        },
        {
            "user": "Sheepyboy",
            "link": "https://youtu.be/J40W6dKcPq4",
            "percent": 100,
            "hz": 360
        },
        {
            "user": "ButterFish",
            "link": "",
            "percent": 100,
            "hz": 360
        },
        {
            "user": "ZircleZ",
            "link": "",
            "percent": 100,
            "hz": 360
        },
        {
            "user": "mk4578",
            "link": "",
            "percent": 100,
            "hz": 360
        },
        {
            "user": "Kuba",
            "link": "",
            "percent": 100,
            "hz": 360
        },
        {
            "user": "ox1y1gen",
            "link": "",
            "percent": 100,
            "hz": 360
        },
        {
            "user": "Yoloplex",
            "link": "",
            "percent": 100,
            "hz": 360
        },
        {
            "user": "Yzae",
            "link": "",
            "percent": 100,
            "hz": 360
        },
        {
            "user": "Aquatic51",
            "link": "",
            "percent": 100,
            "hz": 360
        },
        {
            "user": "Frogs65",
            "link": "",
            "percent": 100,
            "hz": 360
        },
        {
            "user": "kilodiv",
            "link": "https://youtu.be/cNQINEtda34",
            "percent": 100,
            "hz": 360
        },
        {
            "user": "Identity",
            "link": "",
            "percent": 100,
            "hz": 360
        },
        {
            "user": "tomm",
            "link": "",
            "percent": 100,
            "hz": 360
        },
        {
            "user": "Syne",
            "link": "",
            "percent": 100,
            "hz": 360
        },
        {
            "user": "TheoSi",
            "link": "",
            "percent": 100,
            "hz": 360
        }
    ]
}
